LICENSE
MANIFEST.in
README.md
requirements.txt
setup.py
repr_rw/__init__.py
repr_rw/repr_rw.py
repr_rw.egg-info/PKG-INFO
repr_rw.egg-info/SOURCES.txt
repr_rw.egg-info/dependency_links.txt
repr_rw.egg-info/requires.txt
repr_rw.egg-info/top_level.txt