Metadata-Version: 2.1
Name: repr-rw
Version: 3.0.2
Summary: This library writes object representations in a text file and reads the file to recreate the objects. An object representation is a string returned by function repr.
Home-page: https://github.com/GRV96/repr_rw
Author: Guyllaume Rousseau
License: MIT
Classifier: Development Status :: 5 - Production/Stable
Classifier: Intended Audience :: Developers
Classifier: License :: OSI Approved :: MIT License
Classifier: Operating System :: OS Independent
Classifier: Programming Language :: Python :: 3
Classifier: Topic :: Software Development :: Libraries :: Python Modules
Classifier: Topic :: Utilities
License-File: LICENSE
